Workbook

Sheet Config
A1: Stock Analyst Agent — Configuration
A3: Parameter | B3: Value | C3: Notes
A4: Technical Weight | B4: 0.3 | C4: Category weight applied to Overall Score. From framework.json.
A5: Fundamental Weight | B5: 0.4 | C5: Category weight applied to Overall Score. From framework.json.
A6: Sentiment Weight | B6: 0.3 | C6: Category weight applied to Overall Score. From framework.json.
A7: Buy Threshold (>=) | B7: 7 | C7: Overall Score at/above this value -> BUY (or BUY (add) if a position is already held).
A8: Sell/No-Action Threshold (<) | B8: 4.5 | C8: Overall Score below this value -> SELL (if held) / NO ACTION (if not held).
A9: Data Source Mode | B9: web_search | C9: web_search (default) or api. Set by user approval at pipeline kickoff.
A10: Generated At | B10: 2026-09-06T00:00:00Z | C10: Framework generation timestamp (Agent 1).

Sheet Analysis
A1: Stock Info & Tracking | F1: TABLE 1 — Actual Values: Technical | K1: TABLE 1 — Actual Values: Fundamental | P1: TABLE 1 — Actual Values: Sentiment | T1: TABLE 2 — Scores /10: Technical | Y1: TABLE 2 — Scores /10: Fundamental | AD1: TABLE 2 — Scores /10: Sentiment | AH1: Category / Overall / Decision | AM1: Agent Notes
A2: Ticker | B2: Company | C2: State | D2: Review Date | E2: Previous Decision | F2: SMA Trend (50D/200D) (Value) | G2: RSI(14) (Value) | H2: MACD Signal (Value) | I2: Volume Trend (Value) | J2: 52-Week Range Position (Value) | K2: P/E vs. Sector/Historical (Value) | L2: Revenue Growth YoY (Value) | M2: Profit Margin Trend (Value) | N2: Debt-to-Equity (Value) | O2: FCF / EPS Growth (Value) | P2: Analyst Consensus & Price Target (Value) | Q2: Recent News Sentiment (Value) | R2: Short Interest (Value) | S2: Insider Activity (Value) | T2: SMA Trend (50D/200D) (Score) | U2: RSI(14) (Score) | V2: MACD Signal (Score) | W2: Volume Trend (Score) | X2: 52-Week Range Position (Score) | Y2: P/E vs. Sector/Historical (Score) | Z2: Revenue Growth YoY (Score) | AA2: Profit Margin Trend (Score) | AB2: Debt-to-Equity (Score) | AC2: FCF / EPS Growth (Score) | AD2: Analyst Consensus & Price Target (Score) | AE2: Recent News Sentiment (Score) | AF2: Short Interest (Score) | AG2: Insider Activity (Score) | AH2: Technical Score | AI2: Fundamental Score | AJ2: Sentiment Score | AK2: Overall Score | AL2: Decision | AM2: Technical Notes | AN2: Fundamental Notes | AO2: Sentiment Notes
A3: NVDA | B3: Nvidia Corp | C3: No Position | D3: 2026-09-06 | F3: Price $230.36 above 50D SMA $224.03 and above 200D SMA $216.67; 50D>200D (golden cross regime); 9 of 12 MAs give buy signal | G3: 58.30 (neutral) | H3: MACD(12,26) = 2.22, buy signal (positive/rising) | I3: Volume rose ~671K shares vs prior day alongside rising price — accumulation signal | J3: $230.36 vs range $164.07–$236.54 = ~91.5th percentile | K3: Trailing P/E 29.13 vs. Semiconductors industry median 35.94 (19% below) and own 5-yr avg P/E ~61.97 (FY22-FY26: 58.55, 114.74, 50.65, 47.93, 37.98) — 53% below own history. Undervalued on both counts. | L3: TTM revenue $302,970M, +83.38% YoY (vs FY2025 $130,497M) | M3: Net margin 63.66% (TTM) vs 55.85% FY2025, expanding +7.81 pts; operating margin 65.21% vs 62.42% | N3: 0.17x — conservative leverage, well below the semiconductor peer norm | O3: TTM FCF $127,006M (+76.34% YoY); Diluted EPS $7.91, +125.28% YoY | P3: Consensus: Strong Buy (60 analysts polled). Avg price target $325.99 vs current price $230.36 = +41.5% implied upside. Range: $180-$515. | Q3: Predominantly positive. (1) Q2 FY2027 earnings (Aug 26) beat estimates; CEO Jensen Huang forecast ~70% revenue growth for FY2028, far above analyst estimates. (2) Nvidia secured approval to export H200 AI chips to China, a positive regulatory/commercial development, though shares were volatile ('slips despite China push') on profit-taking around the news. (3) Continued strong AI-chip demand narrative reiterated post-earnings. | R3: Short interest 1.23% of float (285.96M shares); 1.18% of shares outstanding. | S3: Net insider selling over trailing months: 12 insiders sold vs. 0 bought (~$1.54B in selling, trailing 12mo, with concentrated recent sales continuing through Aug/Sept 2026 e.g. Director Mark Stevens' $128.9M sale on 8/31/2026). No offsetting buys. | T3: 9 | U3: 6 | V3: 8 | W3: 8 | X3: 9 | Y3: 9 | Z3: 10 | AA3: 9 | AB3: 9 | AC3: 10 | AD3: 9 | AE3: 8 | AF3: 9 | AG3: 2 | AH3: =IFERROR(AVERAGE(T3:X3),"") -> 8 | AI3: =IFERROR(AVERAGE(Y3:AC3),"") -> 9.4 | AJ3: =IFERROR(AVERAGE(AD3:AG3),"") -> 7 | AK3: =IFERROR(AH3*Config!$B$4+AI3*Config!$B$5+AJ3*Config!$B$6,"") -> 8.26 | AL3: =IF(AK3="","",IF(UPPER(C3)="NO POSITION",IF(AK3>=Config!$B$7,"BUY","NO ACTION"),IF(AK3>=Config!$B$7,"BUY (add)",IF(AK3<Config!$B$8,"SELL","HOLD")))) -> BUY | AM3: Broadly bullish technical picture: price near 52-week highs, above both key SMAs with 50D>200D, MACD and volume confirming an uptrend. RSI is neutral, not yet overbought. | AN3: All metrics strongly bullish; AI datacenter demand driving growth and margin expansion with minimal leverage and huge FCF. Watch export-control/China risk and rising custom-ASIC competition as forward risks not captured in trailing data. | AO3: Very bullish analyst/short-interest/news picture offset by persistent, large-scale insider selling (common at NVDA given scheduled 10b5-1 plans by Huang, Kress, Puri, Stevens) — treat insider selling as routine liquidity/diversification rather than a bearish signal on fundamentals.
A4: AAPL | B4: Apple Inc | C4: No Position | D4: 2026-09-06 | F4: Price $319.97 below 50D SMA $321.06 (sell) but above 200D SMA $314.37 (buy); mixed — short-term pullback within longer uptrend | G4: 41.96 (neutral, leaning weak) | H4: MACD(12,26) = -0.21, mild sell signal (near zero); note: StockInvest.us 3-month MACD shows a buy signal, so cross-source signals diverge | I4: Volume rose ~2M shares vs prior day while price declined — mild distribution signal | J4: $319.97 vs range $225.95–$344.57 = ~79.3rd percentile | K4: Trailing P/E 36.71 vs. Hardware industry median 25.23 (35% above) and own 5-yr avg P/E ~29.65 (FY21-25: 25.65,24.22,27.60,36.95,33.85) — ~24% above own history. Overvalued both ways. | L4: TTM revenue $466,823M, +14.24% YoY | M4: Net margin 27.62% (TTM) vs 26.91% FY2025, +0.71 pt — roughly flat | N4: 0.78x — moderate leverage (down from 1.52x in FY2025) | O4: TTM FCF $136,683M (+42.11% YoY, reversing FY2025's -9.23%); Diluted EPS $8.72, +32.61% YoY | P4: Consensus: Buy (44 analysts). Avg price target $324.53 vs current price $319.97 = +1.4% upside (within ±10% band despite 'Buy' label). | Q4: Mixed. (1) Apple officially confirmed a Sept 9, 2026 launch event for a foldable 'iPhone Ultra' and iPhone 18 Pro — the first product event under new CEO John Ternus; anticipation is broadly positive with prediction markets assigning ~81% odds of a 2026 foldable launch. (2) BofA warned foldable displays carry higher component costs that could pressure margins, while Morgan Stanley (Moderate Buy) is more bullish, citing 12% YoY iPhone production growth. (3) Q3 FY2026 earnings (late July) beat estimates but shares fell after-hours on cautious guidance — an older but still relevant data point. | R4: Short interest 0.80% of float (116.33M shares); 2.19 days to cover. | S4: Net insider selling: 7 insiders sold vs. 0 bought (~$85.4M trailing 12mo). CEO Tim Cook sold 64,949 shares (~$16.5M) on 4/2/2026; SVP Jennifer Newstead sold ~$1.79M across Aug-Sept 2026. No offsetting purchases. | T4: 6 | U4: 5 | V4: 4 | W4: 3 | X4: 7 | Y4: 3 | Z4: 6 | AA4: 6 | AB4: 6 | AC4: 9 | AD4: 6 | AE4: 6 | AF4: 9 | AG4: 3 | AH4: =IFERROR(AVERAGE(T4:X4),"") -> 5 | AI4: =IFERROR(AVERAGE(Y4:AC4),"") -> 6 | AJ4: =IFERROR(AVERAGE(AD4:AG4),"") -> 6 | AK4: =IFERROR(AH4*Config!$B$4+AI4*Config!$B$5+AJ4*Config!$B$6,"") -> 5.7 | AL4: =IF(AK4="","",IF(UPPER(C4)="NO POSITION",IF(AK4>=Config!$B$7,"BUY","NO ACTION"),IF(AK4>=Config!$B$7,"BUY (add)",IF(AK4<Config!$B$8,"SELL","HOLD")))) -> NO ACTION | AM4: Mixed-to-slightly-bullish. Price sits just below its 50D SMA after a pullback but remains above its 200D SMA and near the upper part of its 52-week range. Note: stockanalysis.com returned a stale cached quote ($234.93, dated Nov 2024) for this ticker during research — discarded in favor of investing.com/marketbeat.com, which agree at $319.97. | AN4: Valuation is the weak spot — trades rich vs. both sector and own history. Underlying fundamentals (margin stability, deleveraging, strong FCF/EPS growth) are solid; revenue growth just below the 15% bullish threshold. | AO4: Note: Tim Cook transitioned from CEO to Executive Chairman in April 2026, with John Ternus now CEO — outside the 2-4 week news window but relevant context for the Sept 9 product event being his first major launch.
A5: GOOGL | B5: Alphabet Inc Class A | C5: No Position | D5: 2026-09-06 | F5: Price $338.46 below 50D SMA $340.02 and below 200D SMA $347.20; 50D<200D (death-cross-style order) — bearish | G5: 45.53 (neutral) | H5: MACD(12,26) = -0.40, sell signal | I5: Volume rose ~2M shares vs prior day while price fell — distribution signal | J5: $338.46 vs range $226.11–$408.61 = ~61.6th percentile | K5: Trailing P/E ~17.0 vs. Interactive Media industry median 15.125 (12.4% above, within threshold) but ~29% below own 5-yr avg P/E ~24.0 (FY21-25: 25.28,19.09,23.79,23.21,28.61). Mixed signal — near sector, cheap vs. own history. | L5: TTM revenue $445,866M, +20.05% YoY (FY2025 was +15.09%) | M5: Operating margin 33.11% (TTM) vs 32.03% FY2025, +1.08 pt (modest expansion). Net margin jumped to 54.75% from 32.81% (+21.9 pts) — this swing is unusually large and likely reflects a one-time gain (e.g., investment/equity revaluation) rather than core operating improvement; operating margin is the more reliable read. | N5: 0.19x — conservative leverage | O5: TTM FCF $53,273M, -20.16% YoY (down from FY2025 $73,266M) due to capex surging to $132.4B; EPS +112.48% YoY (partly reflects the same one-time item noted above) | P5: Consensus: Strong Buy (63 analysts). Avg price target $428.07 vs current price $338.46 = +26.5% upside. | Q5: Predominantly positive. (1) A favorable antitrust ruling described by commentary as 'a big win for Alphabet investors.' (2) Gemini 3.8 model launch cited as lifting AI-momentum sentiment. (3) Stock opened September with gains after its longest monthly losing streak in over a decade, reflecting a sentiment turnaround. | R5: Short interest 0.67% of float (72.71M shares); 2.35 days to cover. | S5: Net insider selling: 8 insiders sold vs. 0 bought (~$209.59M trailing 12mo). CEO Sundar Pichai sold consistently June-Aug 2026 at $349-373/share; other directors/executives also sold. Described as portfolio rebalancing rather than a loss-of-confidence signal. | T5: 3 | U5: 5 | V5: 3 | W5: 3 | X5: 6 | Y5: 7 | Z5: 9 | AA5: 8 | AB5: 9 | AC5: 4 | AD5: 9 | AE5: 8 | AF5: 9 | AG5: 3 | AH5: =IFERROR(AVERAGE(T5:X5),"") -> 4 | AI5: =IFERROR(AVERAGE(Y5:AC5),"") -> 7.4 | AJ5: =IFERROR(AVERAGE(AD5:AG5),"") -> 7.25 | AK5: =IFERROR(AH5*Config!$B$4+AI5*Config!$B$5+AJ5*Config!$B$6,"") -> 6.335 | AL5: =IF(AK5="","",IF(UPPER(C5)="NO POSITION",IF(AK5>=Config!$B$7,"BUY","NO ACTION"),IF(AK5>=Config!$B$7,"BUY (add)",IF(AK5<Config!$B$8,"SELL","HOLD")))) -> NO ACTION | AM5: Bearish-leaning near term: price below both SMAs with the 50D under the 200D, negative MACD, and distribution-style volume. Overall investing.com daily rating was 'Strong Sell'. 52-week position is mid-range. | AN5: Net margin and EPS growth figures are likely inflated by a one-time non-operating item within the TTM window; operating margin and revenue trends (both solidly positive) are more representative. AI-infrastructure capex is pressuring FCF despite strong top-line growth. | AO5: Strongly bullish across analyst, news, and short-interest metrics; insider selling is the lone bearish-scoring metric but is broadly attributed to routine executive diversification rather than negative conviction.
A6: MSFT | B6: Microsoft Corp | C6: No Position | D6: 2026-09-06 | F6: Price $499.70 below 50D SMA $505.31 (sell) but above 200D SMA $487.87 (buy); 50D>200D still — mixed | G6: 42.69 (neutral, leaning weak) | H6: MACD(12,26) = -1.41, sell signal | I6: Volume fell ~6M shares vs prior day while price also fell — light volume on the down day, roughly neutral | J6: $499.70 vs range $349.20–$553.72 = ~73.6th percentile | K6: Trailing P/E ~27.84 vs. Software industry median 20.8 (35% above) but ~11% below own 5-yr avg P/E ~31.22 (FY22-26: 26.41,34.99,37.69,36.31,20.72). Mixed signal, not extreme either way. | L6: TTM revenue $331,839M, +17.79% YoY | M6: Net margin 40.30% (TTM) vs 36.15% FY2025, +4.15 pts expanding; operating margin 46.78% vs 45.62% | N6: 0.29x — conservative leverage | O6: FY2026 FCF $66,987M, -6.46% YoY (from $71,611M) despite 34.35% operating cash flow growth, because capex nearly doubled to $115,948M; EPS +31.60% YoY | P6: Consensus: Strong Buy (55 analysts). Avg price target $571.38 vs current price $499.70 = +14.3% upside. | Q6: Mixed. (1) Microsoft disclosed it will separately report Azure revenue starting FY2027 (Sept 4), revealing $29.4B quarterly / $101.9B FY2026 Azure revenue — a positive transparency move. (2) Stifel raised its price target to $530 citing improving Copilot adoption/AI momentum (Sept 4). (3) Seattle Times and Newsday filed copyright-infringement lawsuits against OpenAI and Microsoft over AI training data (Sept 4-5) — an adverse legal/regulatory headline. | R6: Short interest 0.92% of float (68.54M shares); 1.85 days to cover. | S6: Net insider selling: 6 sellers vs. 1 buyer (~$93.81M sold vs ~$1.99M bought, trailing 12mo). CEO Satya Nadella sold 86,525 shares (~$43.4M) on 9/1/2026; EVPs Takeshi Numoto and Judson Althoff also sold. One small director purchase (~$1.99M) in Feb 2026. | T6: 6 | U6: 5 | V6: 3 | W6: 6 | X6: 7 | Y6: 5 | Z6: 9 | AA6: 9 | AB6: 9 | AC6: 4 | AD6: 8 | AE6: 6 | AF6: 9 | AG6: 3 | AH6: =IFERROR(AVERAGE(T6:X6),"") -> 5.4 | AI6: =IFERROR(AVERAGE(Y6:AC6),"") -> 7.2 | AJ6: =IFERROR(AVERAGE(AD6:AG6),"") -> 6.5 | AK6: =IFERROR(AH6*Config!$B$4+AI6*Config!$B$5+AJ6*Config!$B$6,"") -> 6.45 | AL6: =IF(AK6="","",IF(UPPER(C6)="NO POSITION",IF(AK6>=Config!$B$7,"BUY","NO ACTION"),IF(AK6>=Config!$B$7,"BUY (add)",IF(AK6<Config!$B$8,"SELL","HOLD")))) -> NO ACTION | AM6: Mixed picture: short-term weakness (below 50D SMA, negative MACD, RSI under 50) inside a still-intact longer-term uptrend (above 200D SMA, upper-middle of 52-week range). | AN6: Strong growth, margin expansion and low leverage, but FCF is declining despite record earnings — driven entirely by an unprecedented AI-datacenter capex ramp, a genuine (not one-off) reinvestment trend worth monitoring. | AO6: AI/Copilot momentum and improved Azure disclosure are offset by fresh copyright litigation naming Microsoft and OpenAI, and by continued heavy insider selling led by the CEO.
A7: AMZN | B7: Amazon.com Inc | C7: No Position | D7: 2026-09-06 | F7: Price $258.51 above 50D SMA $258.16 (buy, marginal) but below 200D SMA $262.40 (sell); mixed | G7: 54.60 (neutral) | H7: MACD(12,26) = -0.11, weak sell signal, near zero | I7: Volume rose ~4M shares vs prior day while price fell — distribution signal | J7: $258.51 vs range $196.00–$287.20 = ~68.5th percentile | K7: Trailing P/E 20.79 vs. Retail-Cyclical industry median 16.37 (27% above) but ~52% below own 5-yr avg P/E ~43.25 (FY21,23,24,25: 50.68,51.61,38.94,31.77; FY22 N/A). Mixed signal. | L7: TTM revenue $775,680M, +15.77% YoY | M7: Net margin 17.44% (TTM) vs 10.83% FY2025, +6.61 pts expanding strongly | N7: 0.46x — conservative leverage, improved from prior years | O7: TTM FCF turned negative at -$11,625M (from +$7,695M in FY2025, -76.6%+ swing) as capex hit $173,028M; EPS +89.66% YoY despite the FCF drop | P7: Consensus: Strong Buy (61 analysts). Avg price target $328.17 vs current price $258.51 = +27.0% upside. | Q7: Predominantly negative in the trailing weeks despite a strong Q2 print. (1) The FTC and 22 states sued Amazon's advertising division, alleging it overcharged ~1.2 million advertisers by ~$20B through undisclosed pricing mechanisms — a significant legal/regulatory negative reported as of Sept 2 2026. (2) Analysts flagged capex concerns: Amazon expanded its 2026 capex budget to $220B (projected to reach $370B by 2028), with one analyst estimating ~-$50B free cash flow in both 2027 and 2028. (3) Stock fell ~11% from its August peak amid these concerns, even though Q2 2026 earnings (late July) had beaten estimates with AWS growth accelerating to 37% and revenue topping $200B for the first time. | R7: Short interest 0.97% of float (95.30M shares); 0.88% of shares outstanding. | S7: Net insider selling: 9 insiders sold vs. 0 bought (~$103.95M trailing 12mo), including CEO Andy Jassy (~$5.2M in August), AWS CEO Matthew Garman (~$3.8M in August), CFO Brian Olsavsky, and others. Characterized as scheduled diversification. | T7: 5 | U7: 6 | V7: 4 | W7: 3 | X7: 6 | Y7: 6 | Z7: 8 | AA7: 9 | AB7: 8 | AC7: 3 | AD7: 9 | AE7: 4 | AF7: 9 | AG7: 3 | AH7: =IFERROR(AVERAGE(T7:X7),"") -> 4.8 | AI7: =IFERROR(AVERAGE(Y7:AC7),"") -> 6.8 | AJ7: =IFERROR(AVERAGE(AD7:AG7),"") -> 6.25 | AK7: =IFERROR(AH7*Config!$B$4+AI7*Config!$B$5+AJ7*Config!$B$6,"") -> 6.035 | AL7: =IF(AK7="","",IF(UPPER(C7)="NO POSITION",IF(AK7>=Config!$B$7,"BUY","NO ACTION"),IF(AK7>=Config!$B$7,"BUY (add)",IF(AK7<Config!$B$8,"SELL","HOLD")))) -> NO ACTION | AM7: Largely neutral/mixed: price is essentially at its 50D SMA but below its 200D SMA, RSI and 52-week position both mid-range, MACD flat-to-slightly-negative, and a recent down-day volume pickup is a mild caution flag. | AN7: Margins and EPS growth are excellent, and leverage is conservative, but AWS/AI infrastructure capex has pushed FCF negative — a genuine reinvestment story, not a one-time charge. Valuation looks fair vs. own history but rich vs. peers. | AO7: Note: an earlier ~30,000 corporate-job-cut story circulating in searches is dated October 2025 and was excluded as stale; the FTC advertising lawsuit (Sept 2 2026) is the dominant recent, verified negative catalyst.
A8: TSM | B8: Taiwan Semiconductor Mfg (ADR) | C8: No Position | D8: 2026-09-06 | F8: Price $428.91 above 50D SMA $419.10 and above 200D SMA $416.15; 50D>200D (golden cross regime); 12 of 12 MAs buy | G8: 70.87 (slightly overbought, just above 70) | H8: MACD(12,26) = 2.98, buy signal | I8: Volume rose ~4M shares vs prior day alongside a +2.85% price gain — accumulation signal | J8: $428.91 vs range $230.30–$479.00 = ~79.9th percentile | K8: Trailing P/E 28.35 vs. Semiconductors industry median 35.54 (~20% below, bullish) but ~36% ABOVE own 5-yr avg P/E ~20.89 (FY21-25: 26.92,11.71,18.05,24.07,23.68). Mixed signal. | L8: TTM revenue NT$4,440,492M, +30.56% YoY | M8: Net margin 49.92% (TTM) vs 44.57% FY2025, +5.35 pts expanding | N8: 0.17x — conservative leverage | O8: TTM FCF NT$1,143,556M, +15.21% to +21.95% YoY (source shows both figures across periods); EPS NT$85.49, +53.43% YoY | P8: Consensus: Strong Buy (19 analysts). Avg price target $554.45 vs current price $428.91 = +29.3% upside. | Q8: Predominantly positive. (1) TSMC's August 2026 monthly sales surged 45% year-over-year on buoyant AI chip demand. (2) The company raised its capex and revenue forecasts for 2026 citing growing AI chip demand. (3) Coverage notes chip demand from Nvidia, AMD, and Apple remains a key growth driver, though some commentary questions whether the current valuation already prices in this strength. | R8: Short interest equals 0.62% of shares outstanding (30.16M shares); short % of float not disclosed by this source ('n/a'), so shares-outstanding basis used as the best available proxy — both point to very low bearish positioning. | S8: Net insider BUYING: over 30 insider purchases since early July 2026 (~$800K aggregate), broad-based across the CEO, CFO, COO, multiple SVPs/VPs, and several directors, accelerating after Q2 earnings and a post-earnings stock pullback (~20% decline from highs). Some selling exists but is described as concentrated among a small group of long-tenured employees taking profits, not a broad signal. | T8: 9 | U8: 4 | V8: 8 | W8: 8 | X8: 7 | Y8: 5 | Z8: 9 | AA8: 9 | AB8: 9 | AC8: 10 | AD8: 9 | AE8: 9 | AF8: 9 | AG8: 9 | AH8: =IFERROR(AVERAGE(T8:X8),"") -> 7.2 | AI8: =IFERROR(AVERAGE(Y8:AC8),"") -> 8.4 | AJ8: =IFERROR(AVERAGE(AD8:AG8),"") -> 9 | AK8: =IFERROR(AH8*Config!$B$4+AI8*Config!$B$5+AJ8*Config!$B$6,"") -> 8.22 | AL8: =IF(AK8="","",IF(UPPER(C8)="NO POSITION",IF(AK8>=Config!$B$7,"BUY","NO ACTION"),IF(AK8>=Config!$B$7,"BUY (add)",IF(AK8<Config!$B$8,"SELL","HOLD")))) -> BUY | AM8: Strongly bullish technical setup across nearly every measure (golden cross regime, rising volume on an up day, near 52-week highs) with the one caution being an RSI just over the 70 overbought threshold after a sharp one-day rally. | AN8: Broad-based strength across growth, margins, leverage, and cash generation. Valuation re-rated up vs. its own recent history (AI/foundry demand), though still cheap vs. sector peers. Figures reported in TWD (millions/per-share). | AO8: TSM is the strongest name across all four metrics in this batch — bullish analyst consensus, strong recent operating news, low short interest, and a notable broad-based insider buying wave following a post-earnings pullback.
A9: SPCX | B9: Space Exploration Technologies Corp Class A | C9: No Position | D9: 2026-09-06 | F9: Price $147.95 above 50D SMA $143.69 and above 200D SMA $132.80; 50D>200D (golden cross regime), though shortest-term MAs (5D/10D) show sell after a recent dip | G9: 56.66 (neutral) | H9: MACD(12,26) = 1.58, buy signal | I9: Volume fell alongside a small price decline — described by source as a 'good sign' (volume following price down), roughly neutral | J9: $147.95 vs range $104.83–$225.64 = ~35.7th percentile | K9: P/E not meaningful (net loss). Substituting P/S: Market cap $2.01T / TTM revenue $23.04B ≈ 87x P/S — no comparable sector median found for this hybrid space/telecom/AI business, and no multi-year own history exists (recent IPO). Extremely rich multiple by any conventional standard. | L9: TTM revenue $23.04B, +121.9% YoY; Q2 2026 revenue $6.93-7.8B (sources vary), roughly doubled YoY | M9: TTM net loss -$8.89B on $23.04B revenue (~-38.6% net margin); Q2 2026 alone showed a narrower net loss of $541M on quarterly revenue (~-7% margin for that quarter), suggesting improving quarterly profitability, but a clean YoY point-change in margin could not be confirmed from available sources — pre-IPO reporting comparability is limited. | N9: 0.31x (Total debt $39,708M / Shareholders' equity $127,224M) — conservative leverage | O9: TTM FCF -$32,515M, worsening from FY2025's -$14,121M as capex more than doubled to $42,415M; EPS -$2.27 TTM, no reliable prior-year comparable EPS available (recent IPO) to compute YoY growth | P9: Consensus: Buy (35 analysts, sourced by StockAnalysis.com/S&P Global). Avg price target $222.32 vs current price $147.95 = +50.3% upside. Range $117-$450 (wide dispersion typical of a recent IPO with limited history). | Q9: Predominantly positive, though the earnings print is ~5 weeks old (slightly outside the strict 2-4 week window but the most substantive news available for this new listing). (1) SpaceX's first-ever public Q2 2026 earnings (Aug 4) showed revenue surging 92% YoY to $7.8B, beating Wall Street estimates by nearly $1B. (2) Growth drivers cited: Starlink subscriber growth (~12M subs) and new compute-capacity deals with Anthropic and Google. (3) Some initial after-hours stock softness was reported despite the beat, and SpaceX joined the Nasdaq-100 in July 2026, which caused a two-day post-inclusion price slide (a technical/mechanical effect, not a fundamental negative). | R9: Short interest 12.06% of float (184.39M shares), though only 1.36% of total shares outstanding (float is a small slice of the company given SpaceX's large insider/founder ownership). Elevated float-based short interest for a recent IPO can reflect difficulty borrowing/hedging shares around lockup unlocks rather than pure bearish conviction, and could pose squeeze risk if sentiment turns positive. | S9: Net selling context: early investors and pre-IPO institutional holders are selling into a series of staggered lockup expirations running July-November 2026, largely attributed by commentary to portfolio-concentration management rather than negative views on the company. This is partly offset by mechanical index-fund buying as SpaceX's weight in the Nasdaq-100/Russell 1000/Morningstar indexes increases (~3.4x) with a mid-September rebalance; it is unclear whether this fully offsets sell pressure. | T9: 8 | U9: 6 | V9: 7 | W9: 6 | X9: 5 | Y9: 3 | Z9: 10 | AA9: 4 | AB9: 8 | AC9: 2 | AD9: 9 | AE9: 8 | AF9: 3 | AG9: 3 | AH9: =IFERROR(AVERAGE(T9:X9),"") -> 6.4 | AI9: =IFERROR(AVERAGE(Y9:AC9),"") -> 5.4 | AJ9: =IFERROR(AVERAGE(AD9:AG9),"") -> 5.75 | AK9: =IFERROR(AH9*Config!$B$4+AI9*Config!$B$5+AJ9*Config!$B$6,"") -> 5.805 | AL9: =IF(AK9="","",IF(UPPER(C9)="NO POSITION",IF(AK9>=Config!$B$7,"BUY","NO ACTION"),IF(AK9>=Config!$B$7,"BUY (add)",IF(AK9<Config!$B$8,"SELL","HOLD")))) -> NO ACTION | AM9: As a recently-public, more volatile name, data coverage is thinner than the mega-caps but investing.com/stockanalysis.com/stockinvest.us all had usable current data. Overall picture is bullish on trend structure (price above both key SMAs, 50D>200D) with neutral momentum/volume readings and price sitting well off its 52-week high ($225.64) after a pullback. | AN9: IPO'd June 12, 2026 — only ~3 months of public trading and one reported quarter (Q2 2026) as of this research date, so historical/YoY comparisons are inherently limited and some TTM figures blend pre- and post-IPO periods. Company remains unprofitable and deeply FCF-negative due to massive capex (Starlink, AI infrastructure) but revenue growth is extremely strong and leverage is conservative. Valuation (P/S ~87x) is priced for exceptional future growth, particularly in the AI segment. | AO9: SPCX (SpaceX) went public and began Nasdaq trading in 2026, so analyst coverage/history is comparatively short and price-target dispersion is wide. Short interest and insider-selling readings both likely reflect lockup-expiration mechanics specific to a new IPO rather than pure bearish sentiment — flagged as squeeze/technical risk rather than a fundamental negative signal.
A10: AVGO | B10: Broadcom Inc | C10: No Position | D10: 2026-09-06 | F10: Price $357.90 below 50D SMA $364.45 and below 200D SMA $385.43; 50D<200D (death cross regime) — bearish | G10: 47.16 (neutral) | H10: MACD(12,26) = -2.10, sell signal | I10: Volume fell vs prior day despite a price gain — bearish divergence (weak conviction on the up move) | J10: $357.90 vs range $289.96–$495.00 = ~33.1st percentile | K10: Trailing P/E 45.68 vs. Semiconductors industry median 35.54 (29% above) but ~20% below own 5-yr avg P/E ~56.99 (FY21-25: 34.00,17.07,24.57,133.83,75.48 — note FY2024's 133.83 was likely distorted by VMware-acquisition accounting/one-time items, inflating this average). Mixed/uncertain signal given the historical distortion. | L10: TTM revenue $89,104M, +48.69% YoY | M10: Net margin 42.94% (TTM) vs 36.20% FY2025, +6.74 pts expanding; operating margin 48.59% vs 41.27%. Note: gross margin actually contracted slightly (75.52% vs 77.33%), a mix-shift caveat worth flagging even though bottom-line margins expanded. | N10: 0.60x — moderate leverage | O10: TTM FCF $39,403M, +58.05% YoY (from $26,914M in FY2025); Diluted EPS $7.83, +100.03% YoY | P10: Consensus: Strong Buy (49 analysts). Avg price target $533.41 vs current price $357.90 = +49.0% upside. | Q10: Mixed. Q3 FY2026 earnings (Sept 2) showed revenue of $29.6B (+86% YoY) and AI semiconductor revenue up 221% YoY to $16.7B — strong factual results — but Q4 guidance of $34.8B came in slightly below the $35.03B consensus. Wall Street reaction was cautious: Truist called results 'good, but not stellar' and trimmed its price target to $520 from $550 (still Buy); RBC maintained a Sector Perform citing supply constraints and a high bar for FY2027-28. | R10: Short interest 1.20% of float (56.21M shares); 1.18% of shares outstanding. | S10: Net insider selling: 8 sellers vs. 1 buyer over the trailing filing window (~$639.73M sold vs ~$1.93M bought). Notable sales include Director Henry Samueli (~$128.3M) and CEO Hock Tan (~$24.3M); Director Harry You was the primary/limited buyer (~$1.9M). Note: several of the largest cited transactions date to Dec 2025-Jan 2026, so the '3-month' window in this source may extend slightly further back than usual; still, the clear directional pattern is net selling. | T10: 3 | U10: 5 | V10: 3 | W10: 4 | X10: 5 | Y10: 5 | Z10: 10 | AA10: 9 | AB10: 6 | AC10: 10 | AD10: 9 | AE10: 6 | AF10: 9 | AG10: 2 | AH10: =IFERROR(AVERAGE(T10:X10),"") -> 4 | AI10: =IFERROR(AVERAGE(Y10:AC10),"") -> 8 | AJ10: =IFERROR(AVERAGE(AD10:AG10),"") -> 6.5 | AK10: =IFERROR(AH10*Config!$B$4+AI10*Config!$B$5+AJ10*Config!$B$6,"") -> 6.35 | AL10: =IF(AK10="","",IF(UPPER(C10)="NO POSITION",IF(AK10>=Config!$B$7,"BUY","NO ACTION"),IF(AK10>=Config!$B$7,"BUY (add)",IF(AK10<Config!$B$8,"SELL","HOLD")))) -> NO ACTION | AM10: Bearish technical setup: price below both key SMAs with the 50D under the 200D, negative MACD, and volume not confirming the day's price gain. Investing.com's overall daily rating was 'Strong Sell' despite a post-earnings pullback from highs. | AN10: AI/custom-silicon and software (VMware) demand driving very strong growth, margins, and cash generation. Valuation looks elevated vs. sector but the 'own 5-yr average' comparison is distorted by an anomalous FY2024 P/E spike tied to VMware acquisition accounting, so that leg of the P/E rubric is less reliable here. | AO10: Broadcom's AI-revenue growth remains exceptional in absolute terms, but a guidance print that came in just under consensus produced a cautious ('not stellar') analyst reaction rather than a clear bullish or bearish one.
A11: META | B11: Meta Platforms Inc | C11: No Position | D11: 2026-09-06 | F11: Price $616.77 above 50D SMA $588.21 and above 200D SMA $577.83; 50D>200D (golden cross regime); 10 of 12 MAs buy | G11: 67 (neutral, upper end) | H11: MACD(12,26) = 7.35, buy signal | I11: Volume fell ~4M shares vs prior day despite a price gain — mild bearish divergence (weak conviction) | J11: $616.77 vs range $520.26–$790.80 = ~35.7th percentile | K11: Trailing P/E ~23.24 vs. Interactive Media industry median 15.125 (53.5% above) but roughly in line with own 5-yr avg P/E ~22.37 (FY21-25: 23.77,13.60,23.28,23.70,27.52) and 16% below its 10-yr median of 27.77. Above sector by >15% but not above own history — mixed, not both. | L11: TTM revenue $228,247M, +27.65% YoY | M11: Net margin 29.84% (TTM) vs 30.08% FY2025, -0.24 pt — roughly flat. Operating margin contracted more notably, -3.36 pts (38.08% vs 41.44%), reflecting rising AI infrastructure depreciation/opex — flagged as a caveat even though net margin is within the 'flat' band. | N11: 0.43x — conservative leverage | O11: TTM FCF $40,976M, -18.27% YoY (from $46,109M); Diluted EPS $26.54, -3.75% YoY (negative) | P11: Consensus: Strong Buy (62 analysts). Avg price target $754.77 vs current price $616.77 = +22.4% upside. | Q11: Mixed-to-positive recently. (1) Sept 1 2026: Meta announced 'Muse Voice Transcribe,' a real-time audio/transcription AI model supporting 70+ languages and 20+ speakers. (2) Same day, Meta resolved a major legal matter valued at $17-18B, removing what was described as 'a major legal overhang'; shares rose ~1.1% on the combined news. (3) Offsetting this, Meta continues to fight an FTC appeal seeking to revive antitrust monopolization charges (as of Aug 24 2026) after a district court had earlier rejected the FTC's case — an ongoing legal risk rather than a new negative. Q2 2026 earnings (July 29, slightly outside the window) had also triggered a stock drop on disappointing guidance and shrinking free cash flow tied to AI capex. | R11: Short interest 1.27% of float (28.05M shares out of a 2.20B float). | S11: Net insider selling: 7 insiders sold vs. 0 bought (~$175.58M trailing 12mo). COO Javier Olivan sold consistently through the quarter at $600-680/share; CTO Andrew Bosworth sold ~$4.4M on 8/18/2026; CFO Susan Li also sold in Feb 2026. | T11: 9 | U11: 7 | V11: 9 | W11: 4 | X11: 5 | Y11: 5 | Z11: 9 | AA11: 6 | AB11: 8 | AC11: 3 | AD11: 9 | AE11: 7 | AF11: 9 | AG11: 3 | AH11: =IFERROR(AVERAGE(T11:X11),"") -> 6.8 | AI11: =IFERROR(AVERAGE(Y11:AC11),"") -> 6.2 | AJ11: =IFERROR(AVERAGE(AD11:AG11),"") -> 7 | AK11: =IFERROR(AH11*Config!$B$4+AI11*Config!$B$5+AJ11*Config!$B$6,"") -> 6.62 | AL11: =IF(AK11="","",IF(UPPER(C11)="NO POSITION",IF(AK11>=Config!$B$7,"BUY","NO ACTION"),IF(AK11>=Config!$B$7,"BUY (add)",IF(AK11<Config!$B$8,"SELL","HOLD")))) -> NO ACTION | AM11: Strong trend/momentum signals (golden cross regime, strong positive MACD) offset by a volume divergence (declining volume on an up day) and a price well below its 52-week high after a pullback from highs; note stock is down ~6.6% YTD per MarketBeat. Note: stockanalysis.com returned a stale cached quote ($716.37) for this ticker during research — discarded in favor of investing.com/marketbeat.com, which agree at $616.77. | AN11: Revenue growth remains robust and leverage is conservative, but rising AI-related depreciation/capex is compressing operating margin, FCF, and EPS. Valuation is rich vs. sector peers though not vs. Meta's own trading history. | AO11: Sentiment has improved into early September on the AI product launch and legal settlement, but the underlying trend of heavy AI capex plus ongoing FTC antitrust appeal and steady insider selling temper the picture.
A12: TSLA | B12: Tesla Inc | C12: No Position | D12: 2026-09-06 | F12: Price $354.08 below 50D SMA $358.55 (sell) but above 200D SMA $338.58 (buy); 50D>200D still — mixed after a sharp one-day drop | G12: 42.10 (neutral, leaning weak) | H12: MACD(12,26) = -1.72, sell signal | I12: Volume rose ~1M shares vs prior day amid a sharp -5.92% price drop — distribution signal | J12: $354.08 vs range $297.38–$498.83 = ~28.2nd percentile | K12: Trailing P/E 367.43 (stockanalysis.com) / 327.85 (GuruFocus) vs. Vehicles & Parts industry median ~17.1 (roughly 19-21x median) and own 5-yr avg P/E ~170.43 (FY21-25: 192.54,30.91,52.66,181.82,394.22) — more than double own average. Overvalued by a wide margin both ways. | L12: TTM revenue $103,619M, +11.76% YoY | M12: Net margin 3.67% (TTM) vs 4.00% FY2025, -0.33 pt — roughly flat/slightly contracting but within the ±1 pt neutral band; operating margin 4.13% vs 4.59% (-0.46 pt) | N12: 0.18x — conservative leverage | O12: TTM FCF $5,762M, +3.15% YoY (positive but modest); Diluted EPS $1.08 TTM, -35.64% YoY (negative) | P12: Consensus: Buy, but notably split (16 Strong Buy, 6 Buy, 19 Hold, 2 Sell, 3 Strong Sell across 46 analysts). Avg price target $390.09 vs current price $354.08 = +10.17% upside (just above the 10% bullish threshold, but the wide rating dispersion — over half of analysts at Hold/Sell — argues for a more neutral read than the headline label suggests). | Q12: Predominantly negative in the most recent days. (1) Sept 4 2026: Tesla shares fell ~6% after its Cybercab robotaxi update 'underwhelmed' — the event was restricted/under NDA and left key questions on pricing, production cadence, and regulatory approval unanswered. (2) Same day, NHTSA opened an audit investigation into Tesla's self-certification of the Cybercab over the vehicle's lack of standard safety equipment (steering wheel, pedals, mirrors). (3) Partially offsetting: Tesla shareholders approved Musk's ~$1 trillion pay package earlier in 2026, removing governance/retention uncertainty, though it is highly dilutive and contingent on an ~8.5x market-cap growth target. | R12: Short interest 2.45% of float (69.20M shares); 1.75% of shares outstanding. | S12: Net insider selling: 5 insiders sold vs. 0 bought (~$120.3M trailing 12mo), including Director Kathleen Wilson-Thompson (~$9.99M, April 2026) and CFO Vaibhav Taneja (multiple sales through May-June 2026). | T12: 6 | U12: 5 | V12: 3 | W12: 3 | X12: 5 | Y12: 2 | Z12: 6 | AA12: 5 | AB12: 9 | AC12: 3 | AD12: 7 | AE12: 4 | AF12: 8 | AG12: 3 | AH12: =IFERROR(AVERAGE(T12:X12),"") -> 4.4 | AI12: =IFERROR(AVERAGE(Y12:AC12),"") -> 5 | AJ12: =IFERROR(AVERAGE(AD12:AG12),"") -> 5.5 | AK12: =IFERROR(AH12*Config!$B$4+AI12*Config!$B$5+AJ12*Config!$B$6,"") -> 4.97 | AL12: =IF(AK12="","",IF(UPPER(C12)="NO POSITION",IF(AK12>=Config!$B$7,"BUY","NO ACTION"),IF(AK12>=Config!$B$7,"BUY (add)",IF(AK12<Config!$B$8,"SELL","HOLD")))) -> NO ACTION | AM12: Stock fell sharply (-5.92%) on the latest session on rising volume, pushing RSI and MACD negative and price below its 50D SMA; investing.com's overall daily technical rating was 'Strong Sell' on the day. Longer-term trend (200D SMA) remains intact and 52-week position is in the lower-middle of its range, well off its 52-week high. | AN12: Valuation is dramatically elevated vs. both sector peers and Tesla's own historical range, and EPS has declined sharply YoY despite still-positive FCF — margin pressure from pricing/incentive competition in EVs is a key driver. Low leverage is the one clearly bullish leg. | AO12: Most recent news flow (Cybercab disappointment + NHTSA probe on Sept 4) is clearly negative and coincided with a same-day ~6% share-price drop; this is the dominant sentiment driver right now, only partly offset by the earlier resolution of Musk's pay-package overhang.

Sheet Sources
A1: Ticker | B1: Category | C1: Parameter | D1: Source Name | E1: Source URL | F1: As Of
A2: NVDA | B2: Technical | C2: SMA Trend (50D/200D) | D2: Investing.com Technical Analysis | E2: https://www.investing.com/equities/nvidia-corp-technical | F2: 2026-09-04
A3: NVDA | B3: Technical | C3: RSI(14) | D3: Investing.com Technical Analysis | E3: https://www.investing.com/equities/nvidia-corp-technical | F3: 2026-09-04
A4: NVDA | B4: Technical | C4: MACD Signal | D4: Investing.com Technical Analysis | E4: https://www.investing.com/equities/nvidia-corp-technical | F4: 2026-09-04
A5: NVDA | B5: Technical | C5: Volume Trend | D5: StockInvest.us | E5: https://stockinvest.us/stock/NVDA | F5: 2026-09-04
A6: NVDA | B6: Technical | C6: 52-Week Range Position | D6: StockAnalysis.com | E6: https://stockanalysis.com/stocks/NVDA/ | F6: 2026-09-04
A7: NVDA | B7: Fundamental | C7: P/E vs. Sector/Historical | D7: GuruFocus PE Ratio (TTM) | E7: https://www.gurufocus.com/term/pettm/NVDA | F7: 2026-09-06
A8: NVDA | B8: Fundamental | C8: Revenue Growth YoY | D8: stockanalysis.com/stocks/NVDA/financials | E8: https://stockanalysis.com/stocks/NVDA/financials/ | F8: TTM ended 2026-07-26
A9: NVDA | B9: Fundamental | C9: Profit Margin Trend | D9: stockanalysis.com/stocks/NVDA/financials | E9: https://stockanalysis.com/stocks/NVDA/financials/ | F9: TTM ended 2026-07-26
A10: NVDA | B10: Fundamental | C10: Debt-to-Equity | D10: stockanalysis.com/stocks/NVDA/financials/ratios | E10: https://stockanalysis.com/stocks/NVDA/financials/ratios/ | F10: 2026-09-04
A11: NVDA | B11: Fundamental | C11: FCF / EPS Growth | D11: stockanalysis.com/stocks/NVDA/financials/cash-flow-statement | E11: https://stockanalysis.com/stocks/NVDA/financials/cash-flow-statement/ | F11: TTM ended 2026-07-26
A12: NVDA | B12: Sentiment | C12: Analyst Consensus & Price Target | D12: StockAnalysis.com (S&P Global consensus) | E12: https://stockanalysis.com/stocks/nvda/forecast/ | F12: 2026-09-04
... A141: TSLA | B141: Sentiment | C141: Insider Activity | D141: MarketBeat insider trades | E141: https://www.marketbeat.com/stocks/NASDAQ/TSLA/insider-trades/ | F141: 2026-09-06 (trailing ~3 months)
